cogef/__init__.py
cogef/cogef1d.py
cogef/dcogef.py
cogef/efei.py
cogef/generalized.py
cogef/minmax.py
cogef/mpf.py
cogef/neb.py
cogef/potentials.py
cogef/probability.py
cogef/spring_constant.py
cogef/units.py
cogef/utilities.py
cogef/vibrations.py
cogef/cli/__init__.py
cogef/cli/main.py
cogef/cogef2d/__init__.py
cogef/cogef2d/cogef2d.py
cogef/cogef2d/cogef2in1.py
cogef/cogef2d/dissociation2d.py
cogef/cogef2d/fixed2d.py
cogef/cogef2d/neb.py
cogef/dissociation/__init__.py
cogef/dissociation/barrier.py
cogef/dissociation/diss_old.py
cogef/dissociation/dissociation.py
cogef/dissociation/tabulated_barrier.py
cogef/test/__init__.py
cogef/test/au6harmonic.py
cogef/test/conftest.py
cogef/test/rate_0_1.dat
cogef/test/rate_0_8.dat
cogef/test/rate_1_2.dat
cogef/test/rate_29_11.dat
cogef/test/rate_8_12.dat
cogef/test/rate_CTC-CCC.dat
cogef/test/rate_CTC-TTC.dat
cogef/test/rate_INTER-CTC.dat
cogef/test/rate_INTER-TTC.dat
cogef/test/rate_SP-INTER.dat
cogef/test/test_MPF.py
cogef/test/test_cogef1d.py
cogef/test/test_cogef1d_generalized.py
cogef/test/test_concerted.py
cogef/test/test_dcogef.py
cogef/test/test_efei_pair.py
cogef/test/test_hocut.py
cogef/test/test_minmax.py
cogef/test/test_neb.py
cogef/test/test_probability.py
cogef/test/test_spring_constant.py
cogef/test/test_spring_vibrations.py
cogef/test/test_units.py
cogef/test/dissociate/__init__.py
cogef/test/dissociate/test_barrier_unit.py
cogef/test/dissociate/test_dissociate_integration.py
cogef/test/dissociate/test_tabulated_barrier.py
ase_cogef-23.6.1.dist-info/COPYING
ase_cogef-23.6.1.dist-info/COPYING.LESSER
ase_cogef-23.6.1.dist-info/LICENSE
ase_cogef-23.6.1.dist-info/METADATA
ase_cogef-23.6.1.dist-info/WHEEL
ase_cogef-23.6.1.dist-info/entry_points.txt
ase_cogef-23.6.1.dist-info/top_level.txt
ase_cogef-23.6.1.dist-info/RECORD
