Metadata-Version: 2.1
Name: ase-cogef
Version: 23.6.1
Summary: COnstrained Geometries simulate External Force
Home-page: https://gitedit.gitlab.io/cogef
Maintainer: Michael Walter
Maintainer-email: mcoywalter@gmail.com
License: LGPLv2.1+
Platform: unix
Classifier: Development Status :: 4 - Beta
Classifier: License :: OSI Approved :: GNU Lesser General Public License v2 or later (LGPLv2+)
Classifier: Operating System :: OS Independent
Classifier: Programming Language :: Python :: 3.6
Classifier: Topic :: Scientific/Engineering :: Physics
License-File: LICENSE
License-File: COPYING
License-File: COPYING.LESSER
Requires-Dist: numpy
Requires-Dist: ase
Provides-Extra: docs
Requires-Dist: sphinx ; extra == 'docs'
Requires-Dist: sphinx-rtd-theme ; extra == 'docs'
Requires-Dist: matplotlib ; extra == 'docs'
